duco/__init__.py
duco/duco.py
duco/filters.py
duco/models/Balance.py
duco/models/Miner.py
duco/models/Statistics.py
duco/models/Transaction.py
duco/models/__init__.py
duco-0.1.12.dist-info/METADATA
duco-0.1.12.dist-info/WHEEL
duco-0.1.12.dist-info/top_level.txt
duco-0.1.12.dist-info/RECORD
